odoo/addons/product_internal_reference_generator/README.rst
odoo/addons/product_internal_reference_generator/__init__.py
odoo/addons/product_internal_reference_generator/__manifest__.py
odoo/addons/product_internal_reference_generator/demo/product_code_seq_demo.xml
odoo/addons/product_internal_reference_generator/i18n/es.po
odoo/addons/product_internal_reference_generator/i18n/it.po
odoo/addons/product_internal_reference_generator/i18n/product_internal_reference_generator.pot
odoo/addons/product_internal_reference_generator/models/__init__.py
odoo/addons/product_internal_reference_generator/models/product_code_sequence.py
odoo/addons/product_internal_reference_generator/models/product_product.py
odoo/addons/product_internal_reference_generator/models/product_template.py
odoo/addons/product_internal_reference_generator/models/res_company.py
odoo/addons/product_internal_reference_generator/models/res_config_settings.py
odoo/addons/product_internal_reference_generator/readme/CONTRIBUTORS.rst
odoo/addons/product_internal_reference_generator/readme/DESCRIPTION.rst
odoo/addons/product_internal_reference_generator/readme/ROADMAP.rst
odoo/addons/product_internal_reference_generator/readme/USAGE.rst
odoo/addons/product_internal_reference_generator/security/groups.xml
odoo/addons/product_internal_reference_generator/security/ir.model.access.csv
odoo/addons/product_internal_reference_generator/static/description/icon.png
odoo/addons/product_internal_reference_generator/static/description/index.html
odoo/addons/product_internal_reference_generator/tests/__init__.py
odoo/addons/product_internal_reference_generator/tests/test_product_internal_reference_generator.py
odoo/addons/product_internal_reference_generator/views/product.xml
odoo/addons/product_internal_reference_generator/views/res_config_settings.xml
odoo14_addon_product_internal_reference_generator-14.0.1.1.1.dist-info/METADATA
odoo14_addon_product_internal_reference_generator-14.0.1.1.1.dist-info/WHEEL
odoo14_addon_product_internal_reference_generator-14.0.1.1.1.dist-info/top_level.txt
odoo14_addon_product_internal_reference_generator-14.0.1.1.1.dist-info/RECORD
