Metadata-Version: 2.1
Name: odoo14-addon-product-internal-reference-generator
Version: 14.0.1.1.1
Summary: Product template and variant reference based on sequence
Home-page: https://github.com/OCA/product-attribute
Author: Ilyas, Ooops, Odoo Community Association (OCA)
Author-email: support@odoo-community.org
License: AGPL-3
Platform: UNKNOWN
Classifier: Programming Language :: Python
Classifier: Framework :: Odoo
Classifier: Framework :: Odoo :: 14.0
Classifier: License :: OSI Approved :: GNU Affero General Public License v3
Requires-Python: >=3.6
Requires-Dist: odoo14-addon-base-view-inheritance-extension
Requires-Dist: odoo <14.1dev,>=14.0a
